annif_client.py
annif_client-0.5.0.dist-info/licenses/LICENSE.txt
annif_client-0.5.0.dist-info/METADATA
annif_client-0.5.0.dist-info/WHEEL
annif_client-0.5.0.dist-info/top_level.txt
annif_client-0.5.0.dist-info/RECORD
