Metadata-Version: 2.4
Name: annif-client
Version: 0.5.0
Summary: Python client library for accessing Annif REST API
Home-page: https://github.com/NatLibFi/Annif-client
Author: Osma Suominen
Author-email: osma.suominen@helsinki.fi
Classifier: Programming Language :: Python :: 3
Classifier: License :: OSI Approved :: Apache Software License
Classifier: Operating System :: OS Independent
License-File: LICENSE.txt
Requires-Dist: requests
Provides-Extra: dev
Requires-Dist: bumpversion; extra == "dev"
Requires-Dist: pytest; extra == "dev"
Requires-Dist: responses; extra == "dev"
Dynamic: author
Dynamic: author-email
Dynamic: classifier
Dynamic: description
Dynamic: description-content-type
Dynamic: home-page
Dynamic: license-file
Dynamic: provides-extra
Dynamic: requires-dist
Dynamic: summary
